randbanner/__init__.py
randbanner-2.0.0.dist-info/DESCRIPTION.rst
randbanner-2.0.0.dist-info/METADATA
randbanner-2.0.0.dist-info/RECORD
randbanner-2.0.0.dist-info/WHEEL
randbanner-2.0.0.dist-info/entry_points.txt
randbanner-2.0.0.dist-info/metadata.json
randbanner-2.0.0.dist-info/top_level.txt
