Metadata-Version: 2.0
Name: randbanner
Version: 2.0.0
Summary: Random banner generator with colour support.
Home-page: https://github.com/Jaiz909/randbanner/
Author: Jai Grimshaw
Author-email: randbanner@jaigrimshaw.com
License: MIT
Platform: UNKNOWN
Requires-Dist: clint
Requires-Dist: pyfiglet
